.DS_Store
sport_scraper/.DS_Store
sport_scraper/VERSION
sport_scraper/__init__.py
sport_scraper/base/__init__.py
sport_scraper/base/config.py
sport_scraper/base/utils.py
sport_scraper-0.0.10.dist-info/LICENSE
sport_scraper-0.0.10.dist-info/METADATA
sport_scraper-0.0.10.dist-info/WHEEL
sport_scraper-0.0.10.dist-info/top_level.txt
sport_scraper-0.0.10.dist-info/RECORD
