Metadata-Version: 2.1
Name: sport-scraper
Version: 0.0.10
Summary: Simple web scraper package for gathering sports data from ESPN.com
Home-page: https://github.com/cristobalmitchell/sports-scraper
Author: Cristobal Mitchell
Author-email: cristobalmitchell@gmail.com
License: UNKNOWN
Platform: UNKNOWN
Classifier: Programming Language :: Python :: 3
Classifier: License :: OSI Approved :: MIT License
Classifier: Operating System :: OS Independent
Requires-Python: >=3.6
Requires-Dist: pandas (>=1.0)
Requires-Dist: bs4 (>=0.0.1)
